{
  "version": 2,
  "scraped_at": "2026-04-09T05:27:06.090392+00:00",
  "event_count": 71,
  "events": [
    {
      "id": "ev_ffcd909e",
      "title": "The Doan Gang: Outlaws of the Revolutionat the Mercer Museum",
      "date": "2024-05-04",
      "time": "Various",
      "venue": "Philadelphia",
      "addr": "",
      "lat": 39.9483,
      "lng": -75.1464,
      "cat": "festival",
      "free": false,
      "description": "",
      "source": "visitphilly.com",
      "priority": 1,
      "end_date": "2027-01-01"
    },
    {
      "id": "ev_453e6ed0",
      "title": "52 Weeks of Firsts",
      "date": "2026-01-01",
      "time": "Weekly",
      "venue": "Citywide",
      "addr": "Various",
      "lat": 39.9524,
      "lng": -75.1636,
      "cat": "america250",
      "free": true,
      "description": "Free weekly events honoring Philly firsts. New neighborhood each Saturday.",
      "source": "city",
      "priority": 3,
      "end_date": "2026-12-31"
    },
    {
      "id": "ev_4f872393",
      "title": "Botany of Nationsat The Academy of Natural Sciences",
      "date": "2026-03-28",
      "time": "Various",
      "venue": "Philadelphia",
      "addr": "Philadelphia, PA 19103",
      "lat": 39.9524,
      "lng": -75.1636,
      "cat": "america250",
      "free": false,
      "description": "Discover the plants, cultures and untold Indigenous stories from the Lewis and Clark expedition at The Academy of Natural Sciences.",
      "source": "visitphilly.com",
      "priority": 1,
      "end_date": "2027-02-14"
    },
    {
      "id": "ev_ca9cae13",
      "title": "Radical Americanafrom The Clay Studio",
      "date": "2026-04-09",
      "time": "Various",
      "venue": "Philadelphia",
      "addr": "Philadelphia, PA 19122",
      "lat": 39.9524,
      "lng": -75.1636,
      "cat": "america250",
      "free": false,
      "description": "",
      "source": "visitphilly.com",
      "priority": 1
    },
    {
      "id": "ev_e8f5328c",
      "title": "250th Anniversary Celebrations at Esperanza Arts Center",
      "date": "2026-04-11",
      "time": "Various",
      "venue": "Philadelphia",
      "addr": "Philadelphia, PA 19140",
      "lat": 39.9524,
      "lng": -75.1636,
      "cat": "america250",
      "free": false,
      "description": "",
      "source": "visitphilly.com",
      "priority": 1
    },
    {
      "id": "ev_ffb159cb",
      "title": "A Nation of Artists",
      "date": "2026-04-12",
      "time": "10:00 AM",
      "venue": "Philadelphia Museum of Art",
      "addr": "2600 Benjamin Franklin Pkwy",
      "lat": 39.9656,
      "lng": -75.181,
      "cat": "festival",
      "free": false,
      "description": "1,000+ works across PMA and PAFA. Four centuries of American art.",
      "source": "city",
      "priority": 3,
      "end_date": "2026-09-05"
    },
    {
      "id": "ev_dc4e2f32",
      "title": "A Nation of Artistsat the Philadelphia Museum of Art and Pennsylvania Academy of Fine Arts",
      "date": "2026-04-12",
      "time": "Various",
      "venue": "Philadelphia",
      "addr": "Philadelphia, PA 19130",
      "lat": 39.9524,
      "lng": -75.1636,
      "cat": "festival",
      "free": false,
      "description": "This groundbreaking dual-location exhibition celebrates American creativity with works by both underrepresented and iconic artists.",
      "source": "visitphilly.com",
      "priority": 1
    },
    {
      "id": "ev_1f7fb6f8",
      "title": "1776: The Musicalat Walnut Street Theatre",
      "date": "2026-04-14",
      "time": "Various",
      "venue": "1776 The Musical -- Walnut Street Theatre -- Philadelphia",
      "addr": "1776 The Musical -- Walnut Street Theatre -- Philadelphia, PA -- Official Website",
      "lat": 39.9524,
      "lng": -75.1636,
      "cat": "america250",
      "free": false,
      "description": "",
      "source": "visitphilly.com",
      "priority": 1
    },
    {
      "id": "ev_f383b630",
      "title": "Mural Arts’ Semiquincentennial Projects",
      "date": "2026-04-16",
      "time": "Various",
      "venue": "Philadelphia",
      "addr": "",
      "lat": 39.9524,
      "lng": -75.1636,
      "cat": "america250",
      "free": false,
      "description": "Mural Arts Philadelphia celebrates the nation's 250th anniversary with inspiring artwork, community workshops, new installations and more.",
      "source": "visitphilly.com",
      "priority": 1
    },
    {
      "id": "ev_8312eadd",
      "title": "250th Anniversary Events & Exhibits at the Schwenkfelder Library & Heritage Center",
      "date": "2026-04-17",
      "time": "Various",
      "venue": "Philadelphia",
      "addr": "",
      "lat": 39.9524,
      "lng": -75.1636,
      "cat": "america250",
      "free": false,
      "description": "",
      "source": "visitphilly.com",
      "priority": 1
    },
    {
      "id": "ev_fffe9648",
      "title": "International Day of Monuments & Sites",
      "date": "2026-04-18",
      "time": "Various",
      "venue": "Philadelphia",
      "addr": "Philadelphia, PA  19103",
      "lat": 39.9524,
      "lng": -75.1636,
      "cat": "america250",
      "free": false,
      "description": "International Day of Monuments and Sites is celebrated annually all over the world on April 18th as a way to honor heritage, diversity, community,",
      "source": "visitphilly.com",
      "priority": 1
    },
    {
      "id": "ev_9e13e6a2",
      "title": "250th Anniversary Events at Historic Trappe",
      "date": "2026-04-18",
      "time": "Various",
      "venue": "Philadelphia",
      "addr": "",
      "lat": 39.9524,
      "lng": -75.1636,
      "cat": "america250",
      "free": false,
      "description": "Celebrating the U.S. Semiquincentennial in 2026 Historic Trappe will commemorate the 250th anniversary of the United States in 2026 with three major initiatives across its properties. Visitors will experience how German-speaking people were at the center of the political, military, and religious tensions that swept through Pennsylvania at the founding of the United States. Here",
      "source": "visitphilly.com",
      "priority": 1
    },
    {
      "id": "ev_7d3c7447",
      "title": "New Exhibitions at Weitzman National Museum of American Jewish History",
      "date": "2026-04-23",
      "time": "Various",
      "venue": "PHILADELPHIA",
      "addr": "PHILADELPHIA, Pa. (November 13, 2025) – To mark the 250th anniversary of the United States, the",
      "lat": 39.9524,
      "lng": -75.1636,
      "cat": "festival",
      "free": false,
      "description": "",
      "source": "visitphilly.com",
      "priority": 1
    },
    {
      "id": "ev_58532aa7",
      "title": "America 250 Exhibits & Programming at the Historical Society of Pennsylvania",
      "date": "2026-04-24",
      "time": "Various",
      "venue": "February 22",
      "addr": "February 22, 2026 | 2 p.m. - 5 p.m. | 1300 Locust St., Philadelphia, PA 19107",
      "lat": 39.9524,
      "lng": -75.1636,
      "cat": "festival",
      "free": false,
      "description": "The Historical Society of Pennsylvania is one of the largest family history libraries in the nation, has excellent collections on local and regional history, and offers a manuscript collection renowned for its 17th-, 18th-, and 19th-century holdings. ",
      "source": "visitphilly.com",
      "priority": 1
    },
    {
      "id": "ev_576d69b8",
      "title": "Rising Up: Rocky and the Making of Monumentsat the Philadelphia Museum of Art",
      "date": "2026-04-25",
      "time": "Various",
      "venue": "Philadelphia",
      "addr": "Philadelphia, PA 19130",
      "lat": 39.9524,
      "lng": -75.1636,
      "cat": "festival",
      "free": false,
      "description": "Discover the Philadelphia Museum of Art, home to renowned art collections, groundbreaking exhibitions, and a legacy of creativity and innovation.",
      "source": "visitphilly.com",
      "priority": 1
    },
    {
      "id": "ev_5f15d429",
      "title": "What Now Creative Festival (ArtPhilly)",
      "date": "2026-05-01",
      "time": "Various",
      "venue": "Citywide",
      "addr": "Various locations, Philadelphia, PA",
      "lat": 39.9524,
      "lng": -75.1636,
      "cat": "festival",
      "free": false,
      "description": "10 days of multidisciplinary arts: concerts, theater, dance, visual art, museum experiences from 80+ local artists across iconic Philly venues.",
      "source": "manual",
      "priority": 10,
      "end_date": "2026-05-10"
    },
    {
      "id": "ev_a096d324",
      "title": "World Heritage Month",
      "date": "2026-05-01",
      "time": "Various",
      "venue": "Philadelphia Parks and Recreation",
      "addr": "Philadelphia Parks and Recreation",
      "lat": 39.9524,
      "lng": -75.1636,
      "cat": "america250",
      "free": false,
      "description": "World Heritage Month is a celebration of Philadelphia’s World Heritage City designation.",
      "source": "visitphilly.com",
      "priority": 1
    },
    {
      "id": "ev_0529d170",
      "title": "America 250 at the University of Pennsylvania",
      "date": "2026-05-05",
      "time": "Various",
      "venue": "Philadelphia",
      "addr": "",
      "lat": 39.9524,
      "lng": -75.1636,
      "cat": "festival",
      "free": false,
      "description": "Join us for America 250 at Penn events and exhibits hosted by participating partners across campus.",
      "source": "visitphilly.com",
      "priority": 1
    },
    {
      "id": "ev_7d8808ea",
      "title": "Cirque du Soleil PresentsLuziaat The Fairgrounds at the Greater Philadelphia Expo Center",
      "date": "2026-05-07",
      "time": "Various",
      "venue": "Philadelphia",
      "addr": "",
      "lat": 39.9524,
      "lng": -75.1636,
      "cat": "america250",
      "free": false,
      "description": "LUZIA takes you in a world of acrobatics, music, and stunning visuals, bringing the sights and sounds of Mexico to life. Get your Cirque du Soleil tickets now!",
      "source": "visitphilly.com",
      "priority": 1,
      "end_date": "2026-06-07"
    },
    {
      "id": "ev_f6a7ae1b",
      "title": "PGA Championship",
      "date": "2026-05-11",
      "time": "All Day",
      "venue": "Aronimink Golf Club",
      "addr": "3600 St Davids Rd, Newtown Square",
      "lat": 39.9835,
      "lng": -75.4135,
      "cat": "concert",
      "free": false,
      "description": "One of golf's four majors.",
      "source": "city",
      "priority": 3,
      "end_date": "2026-05-17"
    },
    {
      "id": "ev_3834d33d",
      "title": "108th PGA Championship at Aronimink Golf Club",
      "date": "2026-05-11",
      "time": "Various",
      "venue": "Philadelphia",
      "addr": "",
      "lat": 39.9835,
      "lng": -75.4135,
      "cat": "america250",
      "free": false,
      "description": "One of the four major men’s golf tournaments returns to the Philadelphia region during the year-long semiquincentennial celebration in 2026.",
      "source": "visitphilly.com",
      "priority": 1,
      "end_date": "2026-05-17"
    },
    {
      "id": "ev_bb5c0824",
      "title": "Mahler and Sorey at the Kimmel Center for the Performing Arts",
      "date": "2026-05-16",
      "time": "Various",
      "venue": "Philadelphia",
      "addr": "Philadelphia, PA 19102",
      "lat": 39.9524,
      "lng": -75.1636,
      "cat": "festival",
      "free": false,
      "description": "",
      "source": "visitphilly.com",
      "priority": 1
    },
    {
      "id": "ev_1b8699f3",
      "title": "Philly Jewish Music Festival",
      "date": "2026-05-17",
      "time": "Various",
      "venue": "Philadelphia",
      "addr": "",
      "lat": 39.9524,
      "lng": -75.1636,
      "cat": "festival",
      "free": false,
      "description": "By partnering with regional and national performers, we will transform Philadelphia into a vibrant hub where Jewish musical expression meets mainstream appreciation.",
      "source": "visitphilly.com",
      "priority": 1
    },
    {
      "id": "ev_4579defa",
      "title": "New Galleries at the National Constitution Center",
      "date": "2026-05-20",
      "time": "Various",
      "venue": "Philadelphia",
      "addr": "Philadelphia, PA 19106",
      "lat": 39.9524,
      "lng": -75.1636,
      "cat": "america250",
      "free": false,
      "description": "Celebrate America's Semiquincentennial at the National Constitution Center's new America's Founding gallery, now open in Philadelphia.",
      "source": "visitphilly.com",
      "priority": 1
    },
    {
      "id": "ev_3b36aa14",
      "title": "RiverRink Summerfest",
      "date": "2026-05-23",
      "time": "Daily",
      "venue": "Delaware River Waterfront",
      "addr": "101 S Columbus Blvd, Philadelphia, PA",
      "lat": 39.9459,
      "lng": -75.1416,
      "cat": "festival",
      "free": true,
      "description": "Rides, roller skating, arcade games, minigolf on the waterfront. Free admission, pay-as-you-go activities. Memorial Day through Labor Day.",
      "source": "manual",
      "priority": 10,
      "end_date": "2026-09-01"
    },
    {
      "id": "ev_252de11a",
      "title": "ArtPhillyWhat Now",
      "date": "2026-05-27",
      "time": "Various",
      "venue": "Philadelphia",
      "addr": "",
      "lat": 39.9524,
      "lng": -75.1636,
      "cat": "festival",
      "free": false,
      "description": "The inaugural ArtPhilly: What Now: 2026 festival brings 30-plus exhibitions, performances and art programs to areas throughout Philadelphia.",
      "source": "visitphilly.com",
      "priority": 1,
      "end_date": "2026-07-02"
    },
    {
      "id": "ev_9b24064d",
      "title": "Philadelphia Gay Men’s Chorus:British Invasionat the Independence Seaport Museum",
      "date": "2026-05-28",
      "time": "Various",
      "venue": "Philadelphia",
      "addr": "Philadelphia, PA, 19103",
      "lat": 39.9524,
      "lng": -75.1636,
      "cat": "festival",
      "free": false,
      "description": "The Philadelphia Gay Men's Chorus is proud to announce its 44th season!",
      "source": "visitphilly.com",
      "priority": 1
    },
    {
      "id": "ev_177074d0",
      "title": "Beethoven and Marsalis at the Kimmel Center for the Performing Arts",
      "date": "2026-05-31",
      "time": "Various",
      "venue": "Philadelphia",
      "addr": "Philadelphia, PA 19102",
      "lat": 39.9524,
      "lng": -75.1636,
      "cat": "festival",
      "free": false,
      "description": "",
      "source": "visitphilly.com",
      "priority": 1
    },
    {
      "id": "ev_d051edb9",
      "title": "Chinese Lantern Festival",
      "date": "2026-06-04",
      "time": "6:00 PM - 11:00 PM",
      "venue": "Franklin Square",
      "addr": "200 N 6th St, Philadelphia, PA",
      "lat": 39.9534,
      "lng": -75.1501,
      "cat": "festival",
      "free": false,
      "description": "Dozens of massive handcrafted lanterns celebrating the Year of the Horse + countries in the soccer tournament. Cultural performances, food vendors.",
      "source": "manual",
      "priority": 10,
      "end_date": "2026-08-02"
    },
    {
      "id": "ev_d6df3dd3",
      "title": "Highmark Mann Center for the Performing Arts 50th Anniversary Performance Series",
      "date": "2026-06-04",
      "time": "Various",
      "venue": "Philadelphia",
      "addr": "Philadelphia, PA 19131",
      "lat": 39.9524,
      "lng": -75.1636,
      "cat": "america250",
      "free": false,
      "description": "Highmark Mann Center for the Performing Arts celebrates its 50th anniversary — and the American semiquincentennial — with major performances.",
      "source": "visitphilly.com",
      "priority": 1,
      "end_date": "2026-06-18"
    },
    {
      "id": "ev_997983f7",
      "title": "Philadelphia Chinese Lantern Festival in Franklin Square",
      "date": "2026-06-05",
      "time": "Various",
      "venue": "Philadelphia",
      "addr": "",
      "lat": 39.9534,
      "lng": -75.1501,
      "cat": "festival",
      "free": false,
      "description": "",
      "source": "visitphilly.com",
      "priority": 1
    },
    {
      "id": "ev_092db796",
      "title": "Roots Picnic",
      "date": "2026-06-06",
      "time": "12:00 PM",
      "venue": "Fairmount Park (Belmont Mansion Drive)",
      "addr": "Belmont Mansion Drive, Philadelphia, PA",
      "lat": 39.978,
      "lng": -75.202,
      "cat": "concert",
      "free": false,
      "description": "Jay-Z, Erykah Badu, Kehlani, Brandy, T.I., De La Soul, DJ Jazzy Jeff, Adam Blackstone and more. Philly's signature music festival.",
      "source": "manual",
      "priority": 10
    },
    {
      "id": "ev_8d279e44",
      "title": "Betsy Ross House Flag Fest",
      "date": "2026-06-06",
      "time": "10:00 AM - 5:00 PM",
      "venue": "Betsy Ross House",
      "addr": "239 Arch St, Philadelphia, PA",
      "lat": 39.9529,
      "lng": -75.1446,
      "cat": "america250",
      "free": true,
      "description": "9-day festival with immersive tours, historical re-enactments, Betsy Ross herself. Culminates on Flag Day with unveiling of a never-before-seen artifact.",
      "source": "manual",
      "priority": 10,
      "end_date": "2026-06-14"
    },
    {
      "id": "ev_f9b69a49",
      "title": "Soccer Fan Festival at Lemon Hill",
      "date": "2026-06-11",
      "end_date": "2026-07-13",
      "time": "All Day",
      "venue": "Lemon Hill, Fairmount Park",
      "addr": "Sedgley Dr, Fairmount Park",
      "lat": 39.9715,
      "lng": -75.183,
      "cat": "fifa",
      "free": true,
      "description": "5-week watch party festival. Up to 25K daily. Big screens, food, music.",
      "source": "hardcoded",
      "priority": 5
    },
    {
      "id": "ev_729916b0",
      "title": "FIFA World Cup 26 and FIFA FanFestival",
      "date": "2026-06-11",
      "time": "Various",
      "venue": "Philadelphia",
      "addr": "",
      "lat": 39.9524,
      "lng": -75.1636,
      "cat": "fifa",
      "free": false,
      "description": "The biggest sporting event in the world comes to Philly with a festival and six FIFA World Cup games — including one on America's 250th birthday.",
      "source": "visitphilly.com",
      "priority": 1
    },
    {
      "id": "ev_f5c20c30",
      "title": "TED Democracy Philadelphia: Founding Futures at the Kimmel Center for the Performing Arts",
      "date": "2026-06-13",
      "time": "Various",
      "venue": "Philadelphia",
      "addr": "Philadelphia, PA 19102",
      "lat": 39.9524,
      "lng": -75.1636,
      "cat": "america250",
      "free": false,
      "description": "Visit Philadelphia and TED Democracy present a full day of brand-new TED Talks exploring the evolving story of modern democracy on June 13.",
      "source": "visitphilly.com",
      "priority": 1,
      "end_date": "2026-06-13"
    },
    {
      "id": "ev_e119384e",
      "title": "Odunde Festival",
      "date": "2026-06-14",
      "time": "10:00 AM",
      "venue": "South Philadelphia (23rd & South)",
      "addr": "23rd St & South St, Philadelphia, PA",
      "lat": 39.9435,
      "lng": -75.182,
      "cat": "parade",
      "free": true,
      "description": "Largest African and African-American street festival in the US. African marketplace, music, dance, food from across the diaspora. Second Sunday in June.",
      "source": "manual",
      "priority": 10
    },
    {
      "id": "ev_7c5d2f74",
      "title": "Ivory Coast vs Ecuador",
      "date": "2026-06-14",
      "time": "7:00 PM",
      "venue": "Philadelphia Stadium (Lincoln Financial Field)",
      "addr": "1 Lincoln Financial Field Way",
      "lat": 39.906,
      "lng": -75.168,
      "cat": "fifa",
      "free": false,
      "description": "Group E opener.",
      "source": "hardcoded",
      "ticketUrl": "https://www.fifa.com/tickets",
      "priority": 5
    },
    {
      "id": "ev_209c802a",
      "title": "Mann Center 50th Anniversary Concert",
      "date": "2026-06-18",
      "time": "7:00 PM",
      "venue": "Highmark Mann Center",
      "addr": "5201 Parkside Ave, Philadelphia, PA",
      "lat": 39.977,
      "lng": -75.2105,
      "cat": "concert",
      "free": false,
      "description": "Philadelphia Orchestra commemorative concert celebrating the Mann Center's 50th anniversary and America's 250th. World premiere with The Crossing choir.",
      "source": "manual",
      "priority": 10
    },
    {
      "id": "ev_43a236ab",
      "title": "Brazil vs Haiti",
      "date": "2026-06-19",
      "time": "9:00 PM",
      "venue": "Philadelphia Stadium (Lincoln Financial Field)",
      "addr": "1 Lincoln Financial Field Way",
      "lat": 39.906,
      "lng": -75.168,
      "cat": "fifa",
      "free": false,
      "description": "Group C. Brazil's first match.",
      "source": "hardcoded",
      "ticketUrl": "https://www.fifa.com/tickets",
      "priority": 5
    },
    {
      "id": "ev_7cd154f5",
      "title": "Wawa Welcome America",
      "date": "2026-06-19",
      "time": "All Day",
      "venue": "Benjamin Franklin Pkwy",
      "addr": "Benjamin Franklin Parkway",
      "lat": 39.963,
      "lng": -75.175,
      "cat": "america250",
      "free": true,
      "description": "16 days from Juneteenth to July 4th. Concerts, parades, fireworks.",
      "source": "city",
      "priority": 3,
      "end_date": "2026-07-04"
    },
    {
      "id": "ev_9af503d4",
      "title": "Wawa Welcome America, including the Red, White & Blue To-Do",
      "date": "2026-06-19",
      "time": "Various",
      "venue": "Philadelphia",
      "addr": "Philadelphia, PA 19130",
      "lat": 39.9524,
      "lng": -75.1636,
      "cat": "fireworks",
      "free": false,
      "description": "Philly celebrates independence — and America's 250th birthday — with the 16 days of fireworks, parades, concerts and more.",
      "source": "visitphilly.com",
      "priority": 1,
      "end_date": "2026-07-04"
    },
    {
      "id": "ev_f8aea28a",
      "title": "Pig Iron Theatre Company PresentsFranklin’s Keyat Plays & Players Theatre",
      "date": "2026-06-20",
      "time": "Various",
      "venue": "Philadelphia",
      "addr": "",
      "lat": 39.9582,
      "lng": -75.1736,
      "cat": "america250",
      "free": false,
      "description": "",
      "source": "visitphilly.com",
      "priority": 1
    },
    {
      "id": "ev_ada2ae2c",
      "title": "Juneteenth Parade & Festival",
      "date": "2026-06-21",
      "time": "10:00 AM",
      "venue": "Malcolm X Park",
      "addr": "Pine St & 52nd St",
      "lat": 39.957,
      "lng": -75.159,
      "cat": "parade",
      "free": true,
      "description": "Music, dance, food, celebration of freedom.",
      "source": "city",
      "priority": 3
    },
    {
      "id": "ev_720a0c16",
      "title": "Philadelphia Juneteenth Parade & Festival",
      "date": "2026-06-21",
      "time": "Various",
      "venue": "Philadelphia",
      "addr": "Philadelphia, PA 19143",
      "lat": 39.9524,
      "lng": -75.1636,
      "cat": "parade",
      "free": true,
      "description": "Celebrate freedom, community and culture in Philadelphia at one of the largest daylong Juneteenth celebrations in the country.",
      "source": "visitphilly.com",
      "priority": 1,
      "end_date": "2026-06-21"
    },
    {
      "id": "ev_49b6ee7e",
      "title": "France vs Playoff Winner",
      "date": "2026-06-22",
      "time": "5:00 PM",
      "venue": "Philadelphia Stadium (Lincoln Financial Field)",
      "addr": "1 Lincoln Financial Field Way",
      "lat": 39.906,
      "lng": -75.168,
      "cat": "fifa",
      "free": false,
      "description": "Group I. France faces the playoff winner.",
      "source": "hardcoded",
      "ticketUrl": "https://www.fifa.com/tickets",
      "priority": 5
    },
    {
      "id": "ev_15dae74a",
      "title": "Curaçao vs Ivory Coast",
      "date": "2026-06-25",
      "time": "4:00 PM",
      "venue": "Philadelphia Stadium (Lincoln Financial Field)",
      "addr": "1 Lincoln Financial Field Way",
      "lat": 39.906,
      "lng": -75.168,
      "cat": "fifa",
      "free": false,
      "description": "Group E final matchday.",
      "source": "hardcoded",
      "ticketUrl": "https://www.fifa.com/tickets",
      "priority": 5
    },
    {
      "id": "ev_3a60006e",
      "title": "Croatia vs Ghana",
      "date": "2026-06-27",
      "time": "5:00 PM",
      "venue": "Philadelphia Stadium (Lincoln Financial Field)",
      "addr": "1 Lincoln Financial Field Way",
      "lat": 39.906,
      "lng": -75.168,
      "cat": "fifa",
      "free": false,
      "description": "Group L. Last group stage in Philadelphia.",
      "source": "hardcoded",
      "ticketUrl": "https://www.fifa.com/tickets",
      "priority": 5
    },
    {
      "id": "ev_149a6ab7",
      "title": "Red, White & Blue To-Do",
      "date": "2026-06-28",
      "time": "All Day",
      "venue": "Historic District",
      "addr": "Independence Mall",
      "lat": 39.9489,
      "lng": -75.15,
      "cat": "america250",
      "free": true,
      "description": "Parades, concerts in America's most historic square mile.",
      "source": "city",
      "priority": 3
    },
    {
      "id": "ev_7c05d5a0",
      "title": "New Exhibits at the First Bank of the United States",
      "date": "2026-07-01",
      "time": "Various",
      "venue": "Philadelphia",
      "addr": "Philadelphia, PA 19106",
      "lat": 39.9524,
      "lng": -75.1636,
      "cat": "festival",
      "free": false,
      "description": "The historic building reopens in Philadelphia as a museum exploring the origins of banking in the United States.",
      "source": "visitphilly.com",
      "priority": 1
    },
    {
      "id": "ev_d4d62280",
      "title": "Round of 16 Match",
      "date": "2026-07-04",
      "time": "5:00 PM",
      "venue": "Philadelphia Stadium (Lincoln Financial Field)",
      "addr": "1 Lincoln Financial Field Way",
      "lat": 39.906,
      "lng": -75.168,
      "cat": "fifa",
      "free": false,
      "description": "Knockout round on America's 250th Anniversary.",
      "source": "hardcoded",
      "ticketUrl": "https://www.fifa.com/tickets",
      "priority": 5
    },
    {
      "id": "ev_5e7d23df",
      "title": "July 4th Fireworks & Concert",
      "date": "2026-07-04",
      "time": "8:00 PM",
      "venue": "Art Museum / Parkway",
      "addr": "2600 Benjamin Franklin Pkwy",
      "lat": 39.9656,
      "lng": -75.181,
      "cat": "fireworks",
      "free": true,
      "description": "Nation's biggest July 4th event. Concert + fireworks.",
      "source": "city",
      "priority": 3
    },
    {
      "id": "ev_3ebc3c8f",
      "title": "Valley Forge National Historical Park's 50th Birthday",
      "date": "2026-07-04",
      "time": "Various",
      "venue": "Philadelphia",
      "addr": "",
      "lat": 39.9524,
      "lng": -75.1636,
      "cat": "america250",
      "free": false,
      "description": "",
      "source": "visitphilly.com",
      "priority": 1
    },
    {
      "id": "ev_c3e2f0dd",
      "title": "Semiquincentennial Time Capsules",
      "date": "2026-07-05",
      "time": "Various",
      "venue": "Philadelphia",
      "addr": "",
      "lat": 39.9524,
      "lng": -75.1636,
      "cat": "america250",
      "free": false,
      "description": "America250 is a bipartisan initiative working to engage every American in the 250th anniversary of the United States.",
      "source": "visitphilly.com",
      "priority": 1
    },
    {
      "id": "ev_5f8de24e",
      "title": "Benjamin Franklin Bridge 100th Anniversary Celebration",
      "date": "2026-07-11",
      "time": "Various",
      "venue": "Philadelphia",
      "addr": "",
      "lat": 39.963,
      "lng": -75.175,
      "cat": "america250",
      "free": false,
      "description": "Since opening in 1926, the Ben Franklin Bridge has served as a vital link between Philadelphia and Camden, connecting millions of people across the Delaware River each year. Once the longest suspension bridge in the world, it remains an enduring symbol of engineering innovation and regional pride. A century later, the bridge continues to move our communities forward.",
      "source": "visitphilly.com",
      "priority": 1
    },
    {
      "id": "ev_b5f147e5",
      "title": "Philly Phlotilla on the Schuylkill River & Delaware River",
      "date": "2026-07-11",
      "time": "Various",
      "venue": "Philadelphia",
      "addr": "",
      "lat": 39.9459,
      "lng": -75.1416,
      "cat": "america250",
      "free": false,
      "description": "",
      "source": "visitphilly.com",
      "priority": 1
    },
    {
      "id": "ev_d3d39ff6",
      "title": "MLB All-Star Game",
      "date": "2026-07-14",
      "time": "7:00 PM",
      "venue": "Citizens Bank Park",
      "addr": "1 Citizens Bank Way",
      "lat": 39.9061,
      "lng": -75.1665,
      "cat": "concert",
      "free": false,
      "description": "Baseball returns to Philly for the first time in 30 years.",
      "source": "city",
      "priority": 3
    },
    {
      "id": "ev_c34d9405",
      "title": "Major League Baseball All-Star Game and All-Star Week",
      "date": "2026-07-14",
      "time": "Various",
      "venue": "Philadelphia",
      "addr": "Philadelphia, PA 19148",
      "lat": 39.9524,
      "lng": -75.1636,
      "cat": "america250",
      "free": false,
      "description": "The biggest stars in baseball take to the field at Citizens Bank Park in 2026, just in time for America's 250th birthday celebrations.",
      "source": "visitphilly.com",
      "priority": 1
    },
    {
      "id": "ev_e51394c2",
      "title": "Seeking Profit and Powerat the Independence Seaport Museum",
      "date": "2026-07-19",
      "time": "Various",
      "venue": "Philadelphia",
      "addr": "Philadelphia, PA 19106",
      "lat": 39.9524,
      "lng": -75.1636,
      "cat": "festival",
      "free": false,
      "description": "Here's what to expect at the Independence Seaport Museum, an interactive attraction exploring Philadelphia’s maritime heritage.",
      "source": "visitphilly.com",
      "priority": 1
    },
    {
      "id": "ev_495a7cb3",
      "title": "America’s 250th Celebration in Newtown",
      "date": "2026-08-08",
      "time": "Various",
      "venue": "Philadelphia",
      "addr": "",
      "lat": 39.9524,
      "lng": -75.1636,
      "cat": "america250",
      "free": false,
      "description": "",
      "source": "visitphilly.com",
      "priority": 1
    },
    {
      "id": "ev_db72042b",
      "title": "Freedom Dreamsat the Barnes Foundation",
      "date": "2026-08-09",
      "time": "Various",
      "venue": "Philadelphia",
      "addr": "Philadelphia, PA 19130",
      "lat": 39.9524,
      "lng": -75.1636,
      "cat": "festival",
      "free": true,
      "description": "Experience film, video, and installation by Arthur Jafa, David Hartt, Garrett Bradley, Ja’Tovia Gary, and Tourmaline. April–August 2026",
      "source": "visitphilly.com",
      "priority": 1
    },
    {
      "id": "ev_e1a15d27",
      "title": "Illumination 250 Festival and Drone Show in Haverford Township",
      "date": "2026-08-29",
      "time": "Various",
      "venue": "Philadelphia",
      "addr": "",
      "lat": 39.9524,
      "lng": -75.1636,
      "cat": "festival",
      "free": false,
      "description": "ILLUMINATION 250 Festival presented by Visit Delco - America250PADelco",
      "source": "visitphilly.com",
      "priority": 1,
      "end_date": "2026-08-29"
    },
    {
      "id": "ev_8e5cb090",
      "title": "Philadelphia Cycling Classic",
      "date": "2026-08-30",
      "time": "All Day",
      "venue": "Logan Square / Kelly Drive / Manayunk",
      "addr": "Benjamin Franklin Parkway, Philadelphia, PA",
      "lat": 39.9571,
      "lng": -75.1709,
      "cat": "concert",
      "free": true,
      "description": "Major cycling race returns after hiatus. Route hits Kelly Drive, Strawberry Mansion, Lemon Hill, and the legendary Manayunk Wall.",
      "source": "manual",
      "priority": 10
    },
    {
      "id": "ev_219e420c",
      "title": "From Invisible to Invincible: Honoring the Art of Colorat Historic Strawberry Mansion",
      "date": "2026-09-19",
      "time": "Various",
      "venue": "Philadelphia",
      "addr": "Philadelphia, PA (January 28, 2026) Historic Strawberry Mansion, the largest Fairmount Park Historic House, located at 2450 Strawberry Mansion Drive, recognizes the 100",
      "lat": 39.9524,
      "lng": -75.1636,
      "cat": "festival",
      "free": false,
      "description": "Historic Strawberry Mansion recognizes 100th anniversary of 1926 Committee with Art Show September-November 2026: Honoring the Art of Color September 19 to November 8, 2026 Strawberry Mansion presents an exhibit titled \"From Invisible to Invincible: Honoring the Art of Color\" in recognition of the 100th Anniversary of its Committee of 1926. The exhibit is a celebration of artists who were not perm",
      "source": "visitphilly.com",
      "priority": 1
    },
    {
      "id": "ev_71d9c27a",
      "title": "Let Freedom Ringat Cherry Street Pier",
      "date": "2026-09-27",
      "time": "Various",
      "venue": "Philadelphia",
      "addr": "",
      "lat": 39.9524,
      "lng": -75.1636,
      "cat": "america250",
      "free": true,
      "description": "",
      "source": "visitphilly.com",
      "priority": 1
    },
    {
      "id": "ev_7379b86a",
      "title": "Historic Germantown 2026",
      "date": "2026-10-20",
      "time": "Various",
      "venue": "Philadelphia",
      "addr": "",
      "lat": 39.9524,
      "lng": -75.1636,
      "cat": "america250",
      "free": false,
      "description": "As the nation celebrates the Semiquincentennial, journey to Historic Germantown, Philadelphia, and experience history!",
      "source": "visitphilly.com",
      "priority": 1
    },
    {
      "id": "ev_fe3f97f5",
      "title": "Revolutionary Family: The Biddles & American Independenceat Andalusia Historic House, Gardens & Arboretum",
      "date": "2026-11-13",
      "time": "Various",
      "venue": "Philadelphia",
      "addr": "",
      "lat": 39.9524,
      "lng": -75.1636,
      "cat": "america250",
      "free": false,
      "description": "",
      "source": "visitphilly.com",
      "priority": 1
    },
    {
      "id": "ev_b9bada85",
      "title": "Houses of Declaration in Montgomery County",
      "date": "2026-12-20",
      "time": "Various",
      "venue": "Philadelphia",
      "addr": "",
      "lat": 39.9524,
      "lng": -75.1636,
      "cat": "america250",
      "free": false,
      "description": "Check out all the ways to celebrate the birth of our nation around the region.",
      "source": "visitphilly.com",
      "priority": 1
    },
    {
      "id": "ev_d7c1634f",
      "title": "Washington Crossing Commemorates 250 Years",
      "date": "2026-12-25",
      "time": "Various",
      "venue": "Philadelphia",
      "addr": "",
      "lat": 39.9524,
      "lng": -75.1636,
      "cat": "america250",
      "free": false,
      "description": "Don’t Miss the Boat for a Once-in-a-Lifetime Celebration of America’s 250th Anniversary! The Countdown to 2026 December 25, 2026, marks the 250th anniversary of a pivotal moment in our nation’s founding: George Washington’s daring crossing of the Delaware River. This courageous act, and the military victories that followed, turned the tide of the American Revolution",
      "source": "visitphilly.com",
      "priority": 1
    },
    {
      "id": "ev_926fa9e6",
      "title": "The Declaration's Journeyat the Museum of the American Revolution",
      "date": "2027-01-03",
      "time": "Various",
      "venue": "Philadelphia",
      "addr": "",
      "lat": 39.9483,
      "lng": -75.1464,
      "cat": "america250",
      "free": false,
      "description": "Explore the Declaration of Independence's impact at home and abroad via rare documents, works of art and artifacts from around the world.",
      "source": "visitphilly.com",
      "priority": 1
    },
    {
      "id": "ev_0bbeb230",
      "title": "Sky Hopinka: Red Metal Dustat the Barnes Foundation",
      "date": "2027-01-18",
      "time": "Various",
      "venue": "Philadelphia",
      "addr": "Philadelphia, PA 19130",
      "lat": 39.9524,
      "lng": -75.1636,
      "cat": "festival",
      "free": true,
      "description": "Explore a new installation by artist Sky Hopinka, on view March 2026–January 2027, at the Barnes Foundation. Free and open to the public.",
      "source": "visitphilly.com",
      "priority": 1
    }
  ]
}